{
	"textures": [
		{
			"image": "atlas.png",
			"format": "RGBA8888",
			"size": {
				"w": 326,
				"h": 25
			},
			"scale": 1,
			"frames": [
				{
					"filename": "blood",
					"rotated": false,
					"trimmed": false,
					"sourceSize": {
						"w": 4,
						"h": 4
					},
					"spriteSourceSize": {
						"x": 0,
						"y": 0,
						"w": 4,
						"h": 4
					},
					"frame": {
						"x": 1,
						"y": 1,
						"w": 4,
						"h": 4
					}
				},
				{
					"filename": "SmallKid/SmallKid-1",
					"rotated": false,
					"trimmed": true,
					"sourceSize": {
						"w": 32,
						"h": 32
					},
					"spriteSourceSize": {
						"x": 12,
						"y": 14,
						"w": 9,
						"h": 18
					},
					"frame": {
						"x": 7,
						"y": 1,
						"w": 9,
						"h": 18
					}
				},
				{
					"filename": "SmallKid/SmallKid-2",
					"rotated": false,
					"trimmed": true,
					"sourceSize": {
						"w": 32,
						"h": 32
					},
					"spriteSourceSize": {
						"x": 12,
						"y": 14,
						"w": 9,
						"h": 18
					},
					"frame": {
						"x": 18,
						"y": 1,
						"w": 9,
						"h": 18
					}
				},
				{
					"filename": "SmallKid/SmallKid-3",
					"rotated": false,
					"trimmed": true,
					"sourceSize": {
						"w": 32,
						"h": 32
					},
					"spriteSourceSize": {
						"x": 13,
						"y": 14,
						"w": 9,
						"h": 18
					},
					"frame": {
						"x": 29,
						"y": 1,
						"w": 9,
						"h": 18
					}
				},
				{
					"filename": "SmallKid/SmallKid-4",
					"rotated": false,
					"trimmed": true,
					"sourceSize": {
						"w": 32,
						"h": 32
					},
					"spriteSourceSize": {
						"x": 13,
						"y": 14,
						"w": 9,
						"h": 18
					},
					"frame": {
						"x": 40,
						"y": 1,
						"w": 9,
						"h": 18
					}
				},
				{
					"filename": "SmallKid/SmallKid-5",
					"rotated": false,
					"trimmed": true,
					"sourceSize": {
						"w": 32,
						"h": 32
					},
					"spriteSourceSize": {
						"x": 11,
						"y": 14,
						"w": 11,
						"h": 18
					},
					"frame": {
						"x": 51,
						"y": 1,
						"w": 11,
						"h": 18
					}
				},
				{
					"filename": "SmallKid/SmallKid-6",
					"rotated": false,
					"trimmed": true,
					"sourceSize": {
						"w": 32,
						"h": 32
					},
					"spriteSourceSize": {
						"x": 10,
						"y": 14,
						"w": 11,
						"h": 18
					},
					"frame": {
						"x": 64,
						"y": 1,
						"w": 11,
						"h": 18
					}
				},
				{
					"filename": "SmallKid/SmallKid-7",
					"rotated": false,
					"trimmed": true,
					"sourceSize": {
						"w": 32,
						"h": 32
					},
					"spriteSourceSize": {
						"x": 11,
						"y": 14,
						"w": 11,
						"h": 18
					},
					"frame": {
						"x": 77,
						"y": 1,
						"w": 11,
						"h": 18
					}
				},
				{
					"filename": "SmallKid/SmallKid-8",
					"rotated": false,
					"trimmed": true,
					"sourceSize": {
						"w": 32,
						"h": 32
					},
					"spriteSourceSize": {
						"x": 11,
						"y": 14,
						"w": 11,
						"h": 18
					},
					"frame": {
						"x": 90,
						"y": 1,
						"w": 11,
						"h": 18
					}
				},
				{
					"filename": "FatKid/FatKid-1",
					"rotated": false,
					"trimmed": false,
					"sourceSize": {
						"w": 11,
						"h": 21
					},
					"spriteSourceSize": {
						"x": 0,
						"y": 0,
						"w": 11,
						"h": 21
					},
					"frame": {
						"x": 103,
						"y": 1,
						"w": 11,
						"h": 21
					}
				},
				{
					"filename": "FatKid/FatKid-2",
					"rotated": false,
					"trimmed": false,
					"sourceSize": {
						"w": 11,
						"h": 21
					},
					"spriteSourceSize": {
						"x": 0,
						"y": 0,
						"w": 11,
						"h": 21
					},
					"frame": {
						"x": 116,
						"y": 1,
						"w": 11,
						"h": 21
					}
				},
				{
					"filename": "PoorKid/PoorKid-1",
					"rotated": false,
					"trimmed": false,
					"sourceSize": {
						"w": 9,
						"h": 21
					},
					"spriteSourceSize": {
						"x": 0,
						"y": 0,
						"w": 9,
						"h": 21
					},
					"frame": {
						"x": 129,
						"y": 1,
						"w": 9,
						"h": 21
					}
				},
				{
					"filename": "PoorKid/PoorKid-2",
					"rotated": false,
					"trimmed": false,
					"sourceSize": {
						"w": 9,
						"h": 21
					},
					"spriteSourceSize": {
						"x": 0,
						"y": 0,
						"w": 9,
						"h": 21
					},
					"frame": {
						"x": 140,
						"y": 1,
						"w": 9,
						"h": 21
					}
				},
				{
					"filename": "FatKid/FatKid-3",
					"rotated": false,
					"trimmed": true,
					"sourceSize": {
						"w": 32,
						"h": 32
					},
					"spriteSourceSize": {
						"x": 10,
						"y": 10,
						"w": 13,
						"h": 22
					},
					"frame": {
						"x": 151,
						"y": 1,
						"w": 13,
						"h": 22
					}
				},
				{
					"filename": "FatKid/FatKid-4",
					"rotated": false,
					"trimmed": true,
					"sourceSize": {
						"w": 32,
						"h": 32
					},
					"spriteSourceSize": {
						"x": 10,
						"y": 10,
						"w": 13,
						"h": 22
					},
					"frame": {
						"x": 166,
						"y": 1,
						"w": 13,
						"h": 22
					}
				},
				{
					"filename": "PoorKid/PoorKid-3",
					"rotated": false,
					"trimmed": true,
					"sourceSize": {
						"w": 32,
						"h": 32
					},
					"spriteSourceSize": {
						"x": 10,
						"y": 10,
						"w": 11,
						"h": 22
					},
					"frame": {
						"x": 181,
						"y": 1,
						"w": 11,
						"h": 22
					}
				},
				{
					"filename": "PoorKid/PoorKid-4",
					"rotated": false,
					"trimmed": true,
					"sourceSize": {
						"w": 32,
						"h": 32
					},
					"spriteSourceSize": {
						"x": 12,
						"y": 10,
						"w": 11,
						"h": 22
					},
					"frame": {
						"x": 194,
						"y": 1,
						"w": 11,
						"h": 22
					}
				},
				{
					"filename": "PoorKid/PoorKid-5",
					"rotated": false,
					"trimmed": true,
					"sourceSize": {
						"w": 32,
						"h": 32
					},
					"spriteSourceSize": {
						"x": 10,
						"y": 10,
						"w": 13,
						"h": 22
					},
					"frame": {
						"x": 207,
						"y": 1,
						"w": 13,
						"h": 22
					}
				},
				{
					"filename": "PoorKid/PoorKid-6",
					"rotated": false,
					"trimmed": true,
					"sourceSize": {
						"w": 32,
						"h": 32
					},
					"spriteSourceSize": {
						"x": 10,
						"y": 10,
						"w": 13,
						"h": 22
					},
					"frame": {
						"x": 222,
						"y": 1,
						"w": 13,
						"h": 22
					}
				},
				{
					"filename": "PoorKid/PoorKid-7",
					"rotated": false,
					"trimmed": true,
					"sourceSize": {
						"w": 32,
						"h": 32
					},
					"spriteSourceSize": {
						"x": 10,
						"y": 10,
						"w": 13,
						"h": 22
					},
					"frame": {
						"x": 237,
						"y": 1,
						"w": 13,
						"h": 22
					}
				},
				{
					"filename": "PoorKid/PoorKid-8",
					"rotated": false,
					"trimmed": true,
					"sourceSize": {
						"w": 32,
						"h": 32
					},
					"spriteSourceSize": {
						"x": 10,
						"y": 10,
						"w": 13,
						"h": 22
					},
					"frame": {
						"x": 252,
						"y": 1,
						"w": 13,
						"h": 22
					}
				},
				{
					"filename": "FatKid/FatKid-5",
					"rotated": false,
					"trimmed": true,
					"sourceSize": {
						"w": 32,
						"h": 32
					},
					"spriteSourceSize": {
						"x": 10,
						"y": 9,
						"w": 13,
						"h": 23
					},
					"frame": {
						"x": 267,
						"y": 1,
						"w": 13,
						"h": 23
					}
				},
				{
					"filename": "FatKid/FatKid-6",
					"rotated": false,
					"trimmed": true,
					"sourceSize": {
						"w": 32,
						"h": 32
					},
					"spriteSourceSize": {
						"x": 9,
						"y": 9,
						"w": 13,
						"h": 23
					},
					"frame": {
						"x": 282,
						"y": 1,
						"w": 13,
						"h": 23
					}
				},
				{
					"filename": "FatKid/FatKid-7",
					"rotated": false,
					"trimmed": true,
					"sourceSize": {
						"w": 32,
						"h": 32
					},
					"spriteSourceSize": {
						"x": 10,
						"y": 9,
						"w": 13,
						"h": 23
					},
					"frame": {
						"x": 297,
						"y": 1,
						"w": 13,
						"h": 23
					}
				},
				{
					"filename": "FatKid/FatKid-8",
					"rotated": false,
					"trimmed": true,
					"sourceSize": {
						"w": 32,
						"h": 32
					},
					"spriteSourceSize": {
						"x": 10,
						"y": 9,
						"w": 13,
						"h": 23
					},
					"frame": {
						"x": 312,
						"y": 1,
						"w": 13,
						"h": 23
					}
				}
			]
		}
	],
	"meta": {
		"app": "https://www.codeandweb.com/texturepacker",
		"version": "3.0",
		"smartupdate": "$TexturePacker:SmartUpdate:6a68f43e619339d31c681d0bd6eabd90:b185bfbee0a7cc16f0487f339d11a663:cbce6b53f0f49e0bf15173c25c41f876$"
	}
}
